{"cameraMode":{"drawMode":0,"name":"Shaded","section":"Shading Mode"},"sceneLighting":true,"audioPlay":false,"sceneViewState":{"m_AlwaysRefresh":false,"showFog":true,"showSkybox":false,"showFlares":true,"showImageEffects":true,"showParticleSystems":true,"showVisualEffectGraphs":true,"m_FxEnabled":true},"in2DMode":false,"pivot":{"x":-316.2417297363281,"y":608.5439453125,"z":1434.9061279296875},"rotation":{"x":0.567850649356842,"y":-0.054230790585279468,"z":0.03753267601132393,"w":0.8204852938652039},"size":1439.06396484375,"orthographic":false}